pledger/__init__.py
pledger/csv_loader.py
pledger/main.py
pledger/portfolio.py
pledger/tax.py
pledger/account/__init__.py
pledger/account/account.py
pledger/account/money.py
pledger/account/transfer.py
pledger/account/transfers.py
pledger/interest/__init__.py
pledger/interest/interest.py
personal_ledger-0.1.7.dist-info/METADATA
personal_ledger-0.1.7.dist-info/WHEEL
personal_ledger-0.1.7.dist-info/entry_points.txt
personal_ledger-0.1.7.dist-info/top_level.txt
personal_ledger-0.1.7.dist-info/RECORD
